README.txt
setup.py
asmpy/__init__.py
asmpy.egg-info/PKG-INFO
asmpy.egg-info/SOURCES.txt
asmpy.egg-info/dependency_links.txt
asmpy.egg-info/top_level.txt